nibol/__init__.py
nibol/apis/__init__.py
nibol/apis/booking.py
nibol/apis/building.py
nibol/apis/space.py
nibol/apis/user.py
nibol/client.py
nibol/clients/__init__.py
nibol/clients/async_client.py
nibol/clients/sync_client.py
nibol/exceptions.py
nibol/logger.py
nibol/models/__init__.py
nibol/models/booking.py
nibol/models/building.py
nibol/models/common.py
nibol/models/space.py
nibol/models/user.py
nibol-0.1.3.dist-info/LICENSE
nibol-0.1.3.dist-info/METADATA
nibol-0.1.3.dist-info/WHEEL
nibol-0.1.3.dist-info/RECORD
