Metadata-Version: 2.3
Name: nibol
Version: 0.1.3
Summary: Python SDK for the Nibol API.
License: MIT
Author: Martin Collado
Author-email: info@martincollado.dev
Requires-Python: >=3.12
Classifier: License :: OSI Approved :: MIT License
Classifier: Programming Language :: Python :: 3
Classifier: Programming Language :: Python :: 3.12
Classifier: Programming Language :: Python :: 3.13
Requires-Dist: httpx (>=0.28.1,<0.29.0)
Requires-Dist: pydantic (>=2.10.5,<3.0.0)
Requires-Dist: requests (>=2.32.3,<3.0.0)
Requires-Dist: structlog (>=25.1.0,<26.0.0)
